pymcp/__init__.py
pymcp/__main__.py
pymcp/converter.py
pymcp/utils/__init__.py
pymcp/utils/cursor_config.py
pymcp-0.1.0.dist-info/METADATA
pymcp-0.1.0.dist-info/WHEEL
pymcp-0.1.0.dist-info/entry_points.txt
pymcp-0.1.0.dist-info/top_level.txt
pymcp-0.1.0.dist-info/RECORD
