Metadata-Version: 2.4
Name: pymcp
Version: 0.1.0
Summary: A tool for converting regular Python functions to MCP servers
Author-email: pandas-studio <ontofinance@gmail.com>
License-Expression: MIT
Project-URL: Homepage, https://github.com/tsdata/pymcp
Project-URL: Bug Tracker, https://github.com/tsdata/pymcp/issues
Classifier: Programming Language :: Python :: 3
Classifier: Programming Language :: Python :: 3.10
Classifier: Programming Language :: Python :: 3.11
Classifier: Programming Language :: Python :: 3.12
Classifier: Operating System :: OS Independent
Requires-Python: >=3.10
Requires-Dist: mcp>=0.1.0
